{
  "Id": "82af00c1-2773-48b6-86e4-ff491f5bd0bf",
  "Name": "TbInvest",
  "OriginalName": "TbInvest",
  "NamePlural": "TbInvests",
  "DatabaseTableName": "TbInvest",
  "Namespace": "TbInvests",
  "Type": 1,
  "MasterEntityName": null,
  "MasterEntity": null,
  "BaseClass": "Entity",
  "PageTitle": "TbInvests",
  "MenuIcon": "file-alt",
  "PrimaryKeyType": "int",
  "PreserveCustomCode": true,
  "IsMultiTenant": false,
  "CheckConcurrency": false,
  "BulkDeleteEnabled": true,
  "ShouldCreateUserInterface": true,
  "ShouldCreateBackend": true,
  "ShouldExportExcel": true,
  "ShouldAddMigration": false,
  "ShouldUpdateDatabase": false,
  "CreateTests": true,
  "Properties": [
    {
      "Id": "b9e12963-9171-4f77-85da-5cae021ea831",
      "Name": "BranchCode",
      "Type": "string",
      "EnumType": null,
      "EnumNamespace": null,
      "EnumAngularImport": null,
      "EnumFilePath": null,
      "DefaultValue": null,
      "IsNullable": false,
      "IsRequired": true,
      "IsFilterable": true,
      "AllowEmptyStrings": false,
      "IsTextArea": false,
      "MinLength": null,
      "MaxLength": 20,
      "SortOrder": 0,
      "SortType": 0,
      "Regex": null,
      "EmailValidation": false,
      "ShowOnList": true,
      "ShowOnCreateModal": true,
      "ShowOnEditModal": true,
      "ReadonlyOnEditModal": false,
      "EnumValues": null,
      "IsSelected": true,
      "OrdinalIndex": 1
    },
    {
      "Id": "ba80c054-2699-49e1-8fbe-ab1eada09d83",
      "Name": "BranchId",
      "Type": "int",
      "EnumType": null,
      "EnumNamespace": null,
      "EnumAngularImport": null,
      "EnumFilePath": null,
      "DefaultValue": null,
      "IsNullable": true,
      "IsRequired": false,
      "IsFilterable": true,
      "AllowEmptyStrings": false,
      "IsTextArea": false,
      "MinLength": null,
      "MaxLength": null,
      "SortOrder": 0,
      "SortType": 0,
      "Regex": null,
      "EmailValidation": false,
      "ShowOnList": true,
      "ShowOnCreateModal": true,
      "ShowOnEditModal": true,
      "ReadonlyOnEditModal": false,
      "EnumValues": null,
      "IsSelected": true,
      "OrdinalIndex": 2
    },
    {
      "Id": "e1d1e815-094a-4f4f-8ed4-e5a3f939c5b4",
      "Name": "CompanyId",
      "Type": "int",
      "EnumType": null,
      "EnumNamespace": null,
      "EnumAngularImport": null,
      "EnumFilePath": null,
      "DefaultValue": null,
      "IsNullable": true,
      "IsRequired": false,
      "IsFilterable": true,
      "AllowEmptyStrings": false,
      "IsTextArea": false,
      "MinLength": null,
      "MaxLength": null,
      "SortOrder": 0,
      "SortType": 0,
      "Regex": null,
      "EmailValidation": false,
      "ShowOnList": true,
      "ShowOnCreateModal": true,
      "ShowOnEditModal": true,
      "ReadonlyOnEditModal": false,
      "EnumValues": null,
      "IsSelected": true,
      "OrdinalIndex": 3
    },
    {
      "Id": "d9ad4f30-956e-4055-9e95-a5d031d90154",
      "Name": "CompanyCode",
      "Type": "string",
      "EnumType": null,
      "EnumNamespace": null,
      "EnumAngularImport": null,
      "EnumFilePath": null,
      "DefaultValue": null,
      "IsNullable": false,
      "IsRequired": true,
      "IsFilterable": true,
      "AllowEmptyStrings": false,
      "IsTextArea": false,
      "MinLength": null,
      "MaxLength": 20,
      "SortOrder": 0,
      "SortType": 0,
      "Regex": null,
      "EmailValidation": false,
      "ShowOnList": true,
      "ShowOnCreateModal": true,
      "ShowOnEditModal": true,
      "ReadonlyOnEditModal": false,
      "EnumValues": null,
      "IsSelected": true,
      "OrdinalIndex": 4
    },
    {
      "Id": "00b9a6d6-5e11-4c89-8c0b-8878e48b3037",
      "Name": "ShareNumTotal",
      "Type": "int",
      "EnumType": null,
      "EnumNamespace": null,
      "EnumAngularImport": null,
      "EnumFilePath": null,
      "DefaultValue": null,
      "IsNullable": true,
      "IsRequired": false,
      "IsFilterable": true,
      "AllowEmptyStrings": false,
      "IsTextArea": false,
      "MinLength": null,
      "MaxLength": null,
      "SortOrder": 0,
      "SortType": 0,
      "Regex": null,
      "EmailValidation": false,
      "ShowOnList": true,
      "ShowOnCreateModal": true,
      "ShowOnEditModal": true,
      "ReadonlyOnEditModal": false,
      "EnumValues": null,
      "IsSelected": true,
      "OrdinalIndex": 5
    },
    {
      "Id": "b72ee2fa-e70a-4ce9-8079-f50a99056eb1",
      "Name": "ShareValueTotal",
      "Type": "decimal",
      "EnumType": null,
      "EnumNamespace": null,
      "EnumAngularImport": null,
      "EnumFilePath": null,
      "DefaultValue": null,
      "IsNullable": true,
      "IsRequired": false,
      "IsFilterable": true,
      "AllowEmptyStrings": false,
      "IsTextArea": false,
      "MinLength": null,
      "MaxLength": null,
      "SortOrder": 0,
      "SortType": 0,
      "Regex": null,
      "EmailValidation": false,
      "ShowOnList": true,
      "ShowOnCreateModal": true,
      "ShowOnEditModal": true,
      "ReadonlyOnEditModal": false,
      "EnumValues": null,
      "IsSelected": true,
      "OrdinalIndex": 6
    },
    {
      "Id": "9e0746fc-b527-443c-a517-4e8f2ac26f6f",
      "Name": "Note",
      "Type": "string",
      "EnumType": null,
      "EnumNamespace": null,
      "EnumAngularImport": null,
      "EnumFilePath": null,
      "DefaultValue": null,
      "IsNullable": true,
      "IsRequired": false,
      "IsFilterable": true,
      "AllowEmptyStrings": false,
      "IsTextArea": false,
      "MinLength": null,
      "MaxLength": 250,
      "SortOrder": 0,
      "SortType": 0,
      "Regex": null,
      "EmailValidation": false,
      "ShowOnList": true,
      "ShowOnCreateModal": true,
      "ShowOnEditModal": true,
      "ReadonlyOnEditModal": false,
      "EnumValues": null,
      "IsSelected": true,
      "OrdinalIndex": 7
    },
    {
      "Id": "a826b2ef-b009-464a-8f5b-9738c5b55ef5",
      "Name": "DocStatus",
      "Type": "byte",
      "EnumType": null,
      "EnumNamespace": null,
      "EnumAngularImport": null,
      "EnumFilePath": null,
      "DefaultValue": null,
      "IsNullable": true,
      "IsRequired": false,
      "IsFilterable": true,
      "AllowEmptyStrings": false,
      "IsTextArea": false,
      "MinLength": null,
      "MaxLength": null,
      "SortOrder": 0,
      "SortType": 0,
      "Regex": null,
      "EmailValidation": false,
      "ShowOnList": true,
      "ShowOnCreateModal": true,
      "ShowOnEditModal": true,
      "ReadonlyOnEditModal": false,
      "EnumValues": null,
      "IsSelected": true,
      "OrdinalIndex": 8
    },
    {
      "Id": "c8f62725-934b-4dc8-845b-e6e893ad7520",
      "Name": "InvestGroup",
      "Type": "bool",
      "EnumType": null,
      "EnumNamespace": null,
      "EnumAngularImport": null,
      "EnumFilePath": null,
      "DefaultValue": null,
      "IsNullable": true,
      "IsRequired": false,
      "IsFilterable": true,
      "AllowEmptyStrings": false,
      "IsTextArea": false,
      "MinLength": null,
      "MaxLength": null,
      "SortOrder": 0,
      "SortType": 0,
      "Regex": null,
      "EmailValidation": false,
      "ShowOnList": true,
      "ShowOnCreateModal": true,
      "ShowOnEditModal": true,
      "ReadonlyOnEditModal": false,
      "EnumValues": null,
      "IsSelected": true,
      "OrdinalIndex": 9
    },
    {
      "Id": "6a273d2f-c1b6-48a5-93da-6a27bfc3814f",
      "Name": "IsActive",
      "Type": "bool",
      "EnumType": null,
      "EnumNamespace": null,
      "EnumAngularImport": null,
      "EnumFilePath": null,
      "DefaultValue": null,
      "IsNullable": true,
      "IsRequired": false,
      "IsFilterable": true,
      "AllowEmptyStrings": false,
      "IsTextArea": false,
      "MinLength": null,
      "MaxLength": null,
      "SortOrder": 0,
      "SortType": 0,
      "Regex": null,
      "EmailValidation": false,
      "ShowOnList": true,
      "ShowOnCreateModal": true,
      "ShowOnEditModal": true,
      "ReadonlyOnEditModal": false,
      "EnumValues": null,
      "IsSelected": true,
      "OrdinalIndex": 10
    },
    {
      "Id": "6272b6b6-4b7c-49e5-8395-ffe5f5c0d83f",
      "Name": "crt_date",
      "Type": "DateTime",
      "EnumType": null,
      "EnumNamespace": null,
      "EnumAngularImport": null,
      "EnumFilePath": null,
      "DefaultValue": null,
      "IsNullable": true,
      "IsRequired": false,
      "IsFilterable": true,
      "AllowEmptyStrings": false,
      "IsTextArea": false,
      "MinLength": null,
      "MaxLength": null,
      "SortOrder": 0,
      "SortType": 0,
      "Regex": null,
      "EmailValidation": false,
      "ShowOnList": true,
      "ShowOnCreateModal": true,
      "ShowOnEditModal": true,
      "ReadonlyOnEditModal": false,
      "EnumValues": null,
      "IsSelected": true,
      "OrdinalIndex": 12
    },
    {
      "Id": "82f65b6a-7ace-44a2-a7e6-76424b5a8b56",
      "Name": "crt_user",
      "Type": "int",
      "EnumType": null,
      "EnumNamespace": null,
      "EnumAngularImport": null,
      "EnumFilePath": null,
      "DefaultValue": null,
      "IsNullable": true,
      "IsRequired": false,
      "IsFilterable": true,
      "AllowEmptyStrings": false,
      "IsTextArea": false,
      "MinLength": null,
      "MaxLength": null,
      "SortOrder": 0,
      "SortType": 0,
      "Regex": null,
      "EmailValidation": false,
      "ShowOnList": true,
      "ShowOnCreateModal": true,
      "ShowOnEditModal": true,
      "ReadonlyOnEditModal": false,
      "EnumValues": null,
      "IsSelected": true,
      "OrdinalIndex": 13
    },
    {
      "Id": "8bb4fcbf-b6af-49bf-abcf-09f3d3304840",
      "Name": "mod_date",
      "Type": "DateTime",
      "EnumType": null,
      "EnumNamespace": null,
      "EnumAngularImport": null,
      "EnumFilePath": null,
      "DefaultValue": null,
      "IsNullable": true,
      "IsRequired": false,
      "IsFilterable": true,
      "AllowEmptyStrings": false,
      "IsTextArea": false,
      "MinLength": null,
      "MaxLength": null,
      "SortOrder": 0,
      "SortType": 0,
      "Regex": null,
      "EmailValidation": false,
      "ShowOnList": true,
      "ShowOnCreateModal": true,
      "ShowOnEditModal": true,
      "ReadonlyOnEditModal": false,
      "EnumValues": null,
      "IsSelected": true,
      "OrdinalIndex": 14
    },
    {
      "Id": "a638c977-457d-4c4b-b7fd-8a04375a7e95",
      "Name": "mod_user",
      "Type": "int",
      "EnumType": null,
      "EnumNamespace": null,
      "EnumAngularImport": null,
      "EnumFilePath": null,
      "DefaultValue": null,
      "IsNullable": true,
      "IsRequired": false,
      "IsFilterable": true,
      "AllowEmptyStrings": false,
      "IsTextArea": false,
      "MinLength": null,
      "MaxLength": null,
      "SortOrder": 0,
      "SortType": 0,
      "Regex": null,
      "EmailValidation": false,
      "ShowOnList": true,
      "ShowOnCreateModal": true,
      "ShowOnEditModal": true,
      "ReadonlyOnEditModal": false,
      "EnumValues": null,
      "IsSelected": true,
      "OrdinalIndex": 15
    }
  ],
  "NavigationProperties": [],
  "NavigationConnections": [],
  "ChildEntities": [],
  "PhysicalFileName": "TbInvest.json"
}